{
  "cli": {
    "version": ">= 7.2.0"
  },
  "build": {
    "base": {
      "node": "20.10.0",
      "ios": {
        "resourceClass": "m-medium"
      }
    },
    "development": {
      "extends": "base",
      "developmentClient": true,
      "distribution": "internal"
    },
    "preview": {
      "extends": "base",
      "distribution": "internal",
      "ios": {
        "simulator": true
      }
    },
    "production": {
      "extends": "base"
    }
  },
  "submit": {
    "production": {}
  }
}
